questest/__init__.py
questest/build_tree.py
questest/commands.py
questest/main.py
questest/navigate_tree.py
questest/tree_node.py
questest-0.1.2.dist-info/LICENSE.md
questest-0.1.2.dist-info/METADATA
questest-0.1.2.dist-info/WHEEL
questest-0.1.2.dist-info/entry_points.txt
questest-0.1.2.dist-info/top_level.txt
questest-0.1.2.dist-info/RECORD
